setup.py
simpleWatch.egg-info/PKG-INFO
simpleWatch.egg-info/SOURCES.txt
simpleWatch.egg-info/dependency_links.txt
simpleWatch.egg-info/entry_points.txt
simpleWatch.egg-info/requires.txt
simpleWatch.egg-info/top_level.txt
src/__init__.py
src/main.py
src/o.py
src/th.py