Metadata-Version: 1.1
Name: simpleWatch
Version: 1.1
Summary: Extemely simple file watcher
Home-page: https://github.com/marcusbuffett/simpleWatch/tree/master
Author: Marcus Buffett
Author-email: marcusbuffett@me.com
License: UNKNOWN
Keywords: file-watcher, watch, file
Platform: UNKNOWN
Classifier: Programming Language :: Python :: 3
